pyrugga/__init__.py
pyrugga/lookup.py
pyrugga/match.py
pyrugga/parse_xml.py
pyrugga/player_summary.sql
pyrugga/timeline.sql
pyrugga/utils.py
pyrugga-1.7.dist-info/LICENSE
pyrugga-1.7.dist-info/METADATA
pyrugga-1.7.dist-info/WHEEL
pyrugga-1.7.dist-info/top_level.txt
pyrugga-1.7.dist-info/RECORD
