Metadata-Version: 2.1
Name: pyrugga
Version: 1.7
Summary: A library to analyse Rugby matches using Opta's SuperScout files
Home-page: https://github.com/jlondal/pyrugga
Author: James Londal
License: GNU AFFERO GENERAL PUBLIC LICENSE
Platform: UNKNOWN
License-File: LICENSE
Requires-Dist: pandas
Requires-Dist: scipy
Requires-Dist: scikit-learn
Requires-Dist: matplotlib
Requires-Dist: statsmodels
Requires-Dist: sqlalchemy
Requires-Dist: duckdb
